<annotation>
    <folder>images</folder>
    <filename>SK-A-270.jpg</filename>
    <size>
        <width>3090</width>
        <height>2760</height>
        <depth>3</depth>
    </size>
    <object>
        <name>person</name>
        <pose>Unspecified</pose>
        <truncated>0</truncated>
        <occluded>0</occluded>
        <difficult>0</difficult>
        <bndbox>
            <xmin>84.000000</xmin>
            <ymin>374.000000</ymin>
            <xmax>1764.000000</xmax>
            <ymax>2755.000000</ymax>
        </bndbox>
    </object>
    <object>
        <name>person</name>
        <pose>Unspecified</pose>
        <truncated>0</truncated>
        <occluded>0</occluded>
        <difficult>0</difficult>
        <bndbox>
            <xmin>1657.000000</xmin>
            <ymin>400.000000</ymin>
            <xmax>3086.000000</xmax>
            <ymax>2761.000000</ymax>
        </bndbox>
    </object>
    <object>
        <name>person</name>
        <pose>Unspecified</pose>
        <truncated>0</truncated>
        <occluded>0</occluded>
        <difficult>0</difficult>
        <bndbox>
            <xmin>580.000000</xmin>
            <ymin>479.000000</ymin>
            <xmax>1762.000000</xmax>
            <ymax>2757.000000</ymax>
        </bndbox>
    </object>
    <object>
        <name>person</name>
        <pose>Unspecified</pose>
        <truncated>0</truncated>
        <occluded>0</occluded>
        <difficult>0</difficult>
        <bndbox>
            <xmin>1487.000000</xmin>
            <ymin>31.000000</ymin>
            <xmax>3017.000000</xmax>
            <ymax>2023.000000</ymax>
        </bndbox>
    </object>
    <object>
        <name>table</name>
        <pose>Unspecified</pose>
        <truncated>0</truncated>
        <occluded>0</occluded>
        <difficult>0</difficult>
        <bndbox>
            <xmin>2137.000000</xmin>
            <ymin>1948.000000</ymin>
            <xmax>3084.000000</xmax>
            <ymax>2754.000000</ymax>
        </bndbox>
    </object>
    <object>
        <name>coins</name>
        <pose>Unspecified</pose>
        <truncated>0</truncated>
        <occluded>0</occluded>
        <difficult>0</difficult>
        <bndbox>
            <xmin>2342.000000</xmin>
            <ymin>1965.000000</ymin>
            <xmax>2759.000000</xmax>
            <ymax>2184.000000</ymax>
        </bndbox>
    </object>
    <object>
        <name>pouch</name>
        <pose>Unspecified</pose>
        <truncated>0</truncated>
        <occluded>0</occluded>
        <difficult>0</difficult>
        <bndbox>
            <xmin>1680.000000</xmin>
            <ymin>2085.000000</ymin>
            <xmax>2151.000000</xmax>
            <ymax>2651.000000</ymax>
        </bndbox>
    </object>
    <object>
        <name>glass</name>
        <pose>Unspecified</pose>
        <truncated>0</truncated>
        <occluded>0</occluded>
        <difficult>0</difficult>
        <bndbox>
            <xmin>2839.000000</xmin>
            <ymin>30.000000</ymin>
            <xmax>3042.000000</xmax>
            <ymax>379.000000</ymax>
        </bndbox>
    </object>
    <object>
        <name>knife kit</name>
        <pose>Unspecified</pose>
        <truncated>0</truncated>
        <occluded>0</occluded>
        <difficult>0</difficult>
        <bndbox>
            <xmin>160.000000</xmin>
            <ymin>2093.000000</ymin>
            <xmax>295.000000</xmax>
            <ymax>2751.000000</ymax>
        </bndbox>
    </object>
</annotation>